LICENSE.txt
MANIFEST.in
README.rst
babel.cfg
prepare-release.sh
pylintrc
requirements.txt
setup.py
translate.py
rhizom/__init__.py
rhizom/alembic.ini
rhizom/database.py
rhizom/defaults.py
rhizom/forms.py
rhizom/lib.py
rhizom/scripts.py
rhizom.egg-info/PKG-INFO
rhizom.egg-info/SOURCES.txt
rhizom.egg-info/dependency_links.txt
rhizom.egg-info/entry_points.txt
rhizom.egg-info/pbr.json
rhizom.egg-info/requires.txt
rhizom.egg-info/top_level.txt
rhizom/migrations/env.py
rhizom/migrations/script.py.mako
rhizom/migrations/versions/3a74acdf7764_graph_center_no_foreign_key.py
rhizom/migrations/versions/44aad8465db3_relationship_primary_key.py
rhizom/migrations/versions/56f7a6c92e27_graph_center.py
rhizom/migrations/versions/947e4289885_add_user_locale.py
rhizom/migrations/versions/b331d042fca_creation_and_access_times.py
rhizom/models/__init__.py
rhizom/models/graph.py
rhizom/models/person.py
rhizom/models/relationship.py
rhizom/models/user.py
rhizom/static/actions.js
rhizom/static/ajax-loader-big.gif
rhizom/static/ajax-loader.gif
rhizom/static/favicon.ico
rhizom/static/graph.css
rhizom/static/graph.js
rhizom/static/logo-24.png
rhizom/static/logo-512.png
rhizom/static/logo-64.png
rhizom/static/signin.png
rhizom/static/style.css
rhizom/static/typeahead.jquery.min.js
rhizom/static/spectrum/spectrum.css
rhizom/static/spectrum/spectrum.js
rhizom/templates/_macros.html
rhizom/templates/admin.html
rhizom/templates/base.html
rhizom/templates/edit.html
rhizom/templates/error.html
rhizom/templates/index.html
rhizom/templates/profile.html
rhizom/templates/users.html
rhizom/templates/view.html
rhizom/templates/admin/edit_accesses.html
rhizom/templates/admin/edit_reltypes.html
rhizom/templates/edit/add_rel.html
rhizom/templates/edit/edit_rel.html
rhizom/templates/edit/new_rel.html
rhizom/tests/__init__.py
rhizom/tests/test_graph_data.py
rhizom/tests/test_import_export.py
rhizom/tests/test_models_graph.py
rhizom/tests/test_view_admin.py
rhizom/tests/test_views_basic.py
rhizom/translations/ca/LC_MESSAGES/messages.mo
rhizom/translations/ca/LC_MESSAGES/messages.po
rhizom/translations/fr/LC_MESSAGES/messages.mo
rhizom/translations/fr/LC_MESSAGES/messages.po
rhizom/views/__init__.py
