Metadata-Version: 1.1
Name: rhizom
Version: 0.5.1
Summary: Visualize your relationships
Home-page: https://gitlab.com/abompard/rhizom
Author: Aurelien Bompard
Author-email: aurelien@bompard.org
License: AGPLv3+
Platform: UNKNOWN
Classifier: Development Status :: 3 - Alpha
Classifier: License :: OSI Approved :: GNU Affero General Public License v3 or later (AGPLv3+)
Classifier: Programming Language :: Python :: 2
